Metadata-Version: 2.1
Name: nwac
Version: 0.1.1
Summary: Download historical NWAC telemetry and forecast data
Home-page: https://github.com/jakesherman/nwac
Author: jakesherman
Author-email: jake@jakesherman.com
License: MIT License
Download-URL: https://github.com/jakesherman/nwac/archive/v0.1.1.tar.gz
Keywords: snow,nwac,avalanche,telemetry
Platform: UNKNOWN
